sidekick/__init__.py
sidekick/constants.py
sidekick/exceptions.py
sidekick/py.typed
sidekick/setup.py
sidekick/types.py
sidekick/cli/__init__.py
sidekick/cli/commands.py
sidekick/cli/main.py
sidekick/cli/repl.py
sidekick/configuration/__init__.py
sidekick/configuration/defaults.py
sidekick/configuration/models.py
sidekick/configuration/settings.py
sidekick/core/__init__.py
sidekick/core/state.py
sidekick/core/tool_handler.py
sidekick/core/agents/__init__.py
sidekick/core/agents/main.py
sidekick/core/setup/__init__.py
sidekick/core/setup/agent_setup.py
sidekick/core/setup/base.py
sidekick/core/setup/config_setup.py
sidekick/core/setup/coordinator.py
sidekick/core/setup/environment_setup.py
sidekick/core/setup/telemetry_setup.py
sidekick/core/setup/undo_setup.py
sidekick/prompts/system.txt
sidekick/services/__init__.py
sidekick/services/mcp.py
sidekick/services/telemetry.py
sidekick/services/undo_service.py
sidekick/tools/__init__.py
sidekick/tools/base.py
sidekick/tools/read_file.py
sidekick/tools/run_command.py
sidekick/tools/update_file.py
sidekick/tools/write_file.py
sidekick/ui/__init__.py
sidekick/ui/console.py
sidekick/ui/constants.py
sidekick/ui/decorators.py
sidekick/ui/input.py
sidekick/ui/keybindings.py
sidekick/ui/output.py
sidekick/ui/panels.py
sidekick/ui/prompt_manager.py
sidekick/ui/tool_ui.py
sidekick/ui/validators.py
sidekick/utils/__init__.py
sidekick/utils/diff_utils.py
sidekick/utils/file_utils.py
sidekick/utils/system.py
sidekick/utils/text_utils.py
sidekick/utils/user_configuration.py
sidekick_cli-0.5.1.dist-info/licenses/LICENSE
sidekick_cli-0.5.1.dist-info/METADATA
sidekick_cli-0.5.1.dist-info/WHEEL
sidekick_cli-0.5.1.dist-info/entry_points.txt
sidekick_cli-0.5.1.dist-info/top_level.txt
sidekick_cli-0.5.1.dist-info/RECORD
