Metadata-Version: 2.4
Name: sidekick-cli
Version: 0.5.1
Summary: Your agentic CLI developer.
Author-email: Gavin Vickery <gavin@geekforbrains.com>
License-Expression: MIT
Project-URL: Homepage, https://github.com/geekforbrains/sidekick-cli
Project-URL: Repository, https://github.com/geekforbrains/sidekick-cli
Keywords: cli,agent,development,automation
Classifier: Development Status :: 4 - Beta
Classifier: Intended Audience :: Developers
Classifier: Programming Language :: Python :: 3
Classifier: Programming Language :: Python :: 3.10
Classifier: Programming Language :: Python :: 3.11
Classifier: Programming Language :: Python :: 3.12
Classifier: Programming Language :: Python :: 3.13
Classifier: Topic :: Software Development
Classifier: Topic :: Utilities
Requires-Python: >=3.10
License-File: LICENSE
Requires-Dist: prompt_toolkit==3.0.51
Requires-Dist: pydantic-ai[logfire]==0.2.6
Requires-Dist: pygments==2.19.1
Requires-Dist: rich==14.0.0
Requires-Dist: typer==0.15.3
Requires-Dist: sentry_sdk==2.28.0
Provides-Extra: dev
Requires-Dist: build; extra == "dev"
Requires-Dist: black; extra == "dev"
Requires-Dist: flake8; extra == "dev"
Requires-Dist: isort; extra == "dev"
Requires-Dist: pytest; extra == "dev"
Requires-Dist: pytest-cov; extra == "dev"
Dynamic: license-file
